JSD_project/__init__.py
JSD_project/enums_consts.py
JSD_project/gameDSL.tx
JSD_project/interpreter.py
JSD_project/main.py
JSD_project/testGame.game
JSD_project/dsl_classes/__init__.py
JSD_project/dsl_classes/actions.py
JSD_project/dsl_classes/armor.py
JSD_project/dsl_classes/enemy.py
JSD_project/dsl_classes/game_world.py
JSD_project/dsl_classes/general_settings.py
JSD_project/dsl_classes/item.py
JSD_project/dsl_classes/player.py
JSD_project/dsl_classes/region.py
JSD_project/dsl_classes/weapon.py
JSD_project-1.0.dist-info/METADATA
JSD_project-1.0.dist-info/WHEEL
JSD_project-1.0.dist-info/top_level.txt
JSD_project-1.0.dist-info/RECORD
