Metadata-Version: 2.1
Name: JSD_project
Version: 1.0
Summary: Rpg text adventure game maker
Home-page: https://github.com/SimicAleksa/JSD-project
Author: Simic Aleksa
Author-email: aleksadsimic@gmail.com
Classifier: Programming Language :: Python :: 3
Classifier: License :: OSI Approved :: MIT License
Classifier: Operating System :: Microsoft :: Windows
Requires-Python: >=3.9
Requires-Dist: Arpeggio ==2.0.2
Requires-Dist: click ==8.1.7
Requires-Dist: colorama ==0.4.6
Requires-Dist: textX ==4.0.1
Requires-Dist: twine ==5.0.0
Requires-Dist: setuptools ==69.1.0
Requires-Dist: wheel ==0.43.0
